iamzero_boto3/__init__.py
iamzero_boto3-0.1.9.dist-info/WHEEL
iamzero_boto3-0.1.9.dist-info/METADATA
iamzero_boto3-0.1.9.dist-info/RECORD
