Metadata-Version: 2.1
Name: iamzero-boto3
Version: 0.1.9
Summary: The AWS SDK for Python, instrumented with iam-zero
License: Apache-2.0
Author: Chris Norman
Author-email: chris@exponentlabs.io
Requires-Python: >=3.6.2,<4.0.0
Classifier: License :: OSI Approved :: Apache Software License
Classifier: Programming Language :: Python :: 3
Classifier: Programming Language :: Python :: 3.7
Classifier: Programming Language :: Python :: 3.8
Classifier: Programming Language :: Python :: 3.9
Requires-Dist: boto3 (>=1.17.54,<2.0.0)
Requires-Dist: iamzero-botocore (>=0.1.10,<0.2.0)
